asyncmiele/__init__.py
asyncmiele/appliance.py
asyncmiele/capabilities.py
asyncmiele/device_compatibility.py
asyncmiele/enums.py
asyncmiele/py.typed
asyncmiele/subscription.py
asyncmiele/api/__init__.py
asyncmiele/api/client.py
asyncmiele/api/setup_client.py
asyncmiele/config/__init__.py
asyncmiele/config/loader.py
asyncmiele/connection/__init__.py
asyncmiele/connection/health.py
asyncmiele/connection/manager.py
asyncmiele/connection/pool.py
asyncmiele/connection/reset.py
asyncmiele/dop2/__init__.py
asyncmiele/dop2/binary.py
asyncmiele/dop2/client.py
asyncmiele/dop2/explorer.py
asyncmiele/dop2/generation.py
asyncmiele/dop2/models.py
asyncmiele/dop2/parser.py
asyncmiele/dop2/programs.py
asyncmiele/dop2/visualizer.py
asyncmiele/exceptions/__init__.py
asyncmiele/exceptions/api.py
asyncmiele/exceptions/auth.py
asyncmiele/exceptions/config.py
asyncmiele/exceptions/connection.py
asyncmiele/exceptions/network.py
asyncmiele/exceptions/setup.py
asyncmiele/exporters/prometheus.py
asyncmiele/models/__init__.py
asyncmiele/models/credentials.py
asyncmiele/models/device.py
asyncmiele/models/device_profile.py
asyncmiele/models/network_config.py
asyncmiele/models/response.py
asyncmiele/models/summary.py
asyncmiele/programs/__init__.py
asyncmiele/programs/catalog.py
asyncmiele/utils/__init__.py
asyncmiele/utils/crypto.py
asyncmiele/utils/discovery.py
asyncmiele/utils/http_consts.py
asyncmiele/utils/program_parser.py
asyncmiele/utils/provisioning.py
asyncmiele/validation/__init__.py
asyncmiele/validation/config.py
asyncmiele/validation/core.py
asyncmiele-0.2.6.dist-info/licenses/LICENSE
resources/__init__.py
resources/enums.json
resources/programs/washing_machine.json
scripts/__init__.py
scripts/configure_device_wifi.py
scripts/create_device_profile.py
scripts/device_diagnosis.py
scripts/device_factory_reset.py
scripts/discover_setup_devices.py
scripts/dop2_explorer.py
scripts/visualize_dop2_tree.py
asyncmiele-0.2.6.dist-info/METADATA
asyncmiele-0.2.6.dist-info/WHEEL
asyncmiele-0.2.6.dist-info/top_level.txt
asyncmiele-0.2.6.dist-info/RECORD
