Metadata-Version: 2.4
Name: asyncmiele
Version: 0.2.6
Summary: Async Python client for Miele@Home devices
Author: asyncmiele contributors
License-Expression: MIT
Project-URL: Homepage, https://github.com/yourusername/asyncmiele
Project-URL: Bug Tracker, https://github.com/yourusername/asyncmiele/issues
Classifier: Programming Language :: Python :: 3
Classifier: Programming Language :: Python :: 3.11
Classifier: Programming Language :: Python :: 3.12
Classifier: Operating System :: OS Independent
Classifier: Development Status :: 4 - Beta
Classifier: Intended Audience :: Developers
Classifier: Topic :: Home Automation
Requires-Python: >=3.11
License-File: LICENSE
Requires-Dist: aiohttp>=3.8.0
Requires-Dist: pydantic>=2.0.0
Requires-Dist: cryptography>=39.0.0
Requires-Dist: requests>=2.32.3
Provides-Extra: dev
Requires-Dist: pytest>=7.0; extra == "dev"
Requires-Dist: pytest-asyncio>=0.21; extra == "dev"
Dynamic: license-file
